classmemo/__init__.py
classmemo-1.0.2.dist-info/LICENSE.md
classmemo-1.0.2.dist-info/METADATA
classmemo-1.0.2.dist-info/WHEEL
classmemo-1.0.2.dist-info/top_level.txt
classmemo-1.0.2.dist-info/RECORD
