Metadata-Version: 2.1
Name: classmemo
Version: 1.0.2
Summary: Memoizer for classes
Home-page: https://github.com/jonathangjertsen/classmemo
Author: Jonathan Reichelt Gjertsen
Author-email: jonath.re@gmail.com
License: MIT
Platform: UNKNOWN
